Workbook

Sheet README
A1: FuelStation OS Two-Company E2E Test Pack
A2: Purpose | B2: Use this workbook to create two separate tenants, configure stations, and run one complete operations day per station.
A3: Recommended order | B3: Companies -> Stations -> Users -> Products -> Product Prices -> Tanks -> Pumps -> Nozzles -> Debtors -> Daily Sessions -> operational tabs.
A4: Critical note | B4: Dates are written in British display format, e.g. 19-Jun-2026. Import code may normalize them to ISO dates.
A5: Do not import | B5: This workbook is a test/import template. Do not import passwords or internal database IDs.

Sheet Companies
A1: companyCode | B1: tenantName | C1: slug | D1: subscriptionPackage | E1: subscriptionStatus | F1: maxStations | G1: maxTanks | H1: maxPumps | I1: billingEmail | J1: billingAddress | K1: ownerName | L1: ownerEmail
A2: AKF | B2: Akwaaba Energy Ltd | C2: akwaaba-energy | D2: PRO | E2: ACTIVE | F2: 3 | G2: 10 | H2: 8 | I2: accounts@akwaabaenergy.com | J2: 12 Independence Avenue, Accra | K2: Ama Boateng | L2: ama.boateng@akwaabaenergy.com
A3: NBF | B3: Northbridge Fuels Ltd | C3: northbridge-fuels | D3: STARTER | E3: ACTIVE | F3: 1 | G3: 4 | H3: 3 | I3: finance@northbridgefuels.com | J3: Plot 18 Industrial Area, Tamale | K3: Suleman Yakubu | L3: suleman.yakubu@northbridgefuels.com

Sheet Stations
A1: companyCode | B1: stationCode | C1: stationName | D1: location | E1: status
A2: AKF | B2: AKF-AC | C2: Akwaaba Accra Central | D2: Accra Central | E2: ACTIVE
A3: AKF | B3: AKF-KU | C3: Akwaaba Kumasi Ridge | D3: Kumasi Ridge | E3: ACTIVE
A4: NBF | B4: NBF-TA | C4: Northbridge Tamale North | D4: Tamale North | E4: ACTIVE

Sheet Users
A1: companyCode | B1: name | C1: email | D1: role | E1: stationCode | F1: temporaryPasswordPolicy | G1: status
A2: AKF | B2: Ama Boateng | C2: ama.boateng@akwaabaenergy.com | D2: OWNER | F2: Generate temporary password; force reset | G2: ACTIVE
A3: AKF | B3: Kwesi Mensah | C3: kwesi.mensah@akwaabaenergy.com | D3: ADMIN | F3: Generate temporary password; force reset | G3: ACTIVE
A4: AKF | B4: Linda Owusu | C4: linda.owusu@akwaabaenergy.com | D4: STATION_MANAGER | E4: AKF-AC | F4: Generate temporary password; force reset | G4: ACTIVE
A5: AKF | B5: Kojo Armah | C5: kojo.armah@akwaabaenergy.com | D5: SUPERVISOR | E5: AKF-AC | F5: Generate temporary password; force reset | G5: ACTIVE
A6: AKF | B6: Adwoa Serwaa | C6: adwoa.serwaa@akwaabaenergy.com | D6: ATTENDANT | E6: AKF-AC | F6: Generate temporary password; force reset | G6: ACTIVE
A7: AKF | B7: Nana Agyekum | C7: nana.agyekum@akwaabaenergy.com | D7: STATION_MANAGER | E7: AKF-KU | F7: Generate temporary password; force reset | G7: ACTIVE
A8: AKF | B8: Esi Arthur | C8: esi.arthur@akwaabaenergy.com | D8: SUPERVISOR | E8: AKF-KU | F8: Generate temporary password; force reset | G8: ACTIVE
A9: NBF | B9: Suleman Yakubu | C9: suleman.yakubu@northbridgefuels.com | D9: OWNER | F9: Generate temporary password; force reset | G9: ACTIVE
A10: NBF | B10: Aisha Abubakar | C10: aisha.abubakar@northbridgefuels.com | D10: STATION_MANAGER | E10: NBF-TA | F10: Generate temporary password; force reset | G10: ACTIVE
A11: NBF | B11: Issah Mohammed | C11: issah.mohammed@northbridgefuels.com | D11: SUPERVISOR | E11: NBF-TA | F11: Generate temporary password; force reset | G11: ACTIVE

Sheet Products
A1: companyCode | B1: productCode | C1: productName | D1: category | E1: isActive
A2: AKF | B2: S95 | C2: Super 95 | D2: FUEL | E2: TRUE
A3: AKF | B3: S91 | C3: Super 91 | D3: FUEL | E3: TRUE
A4: AKF | B4: AGO | C4: Diesel | D4: FUEL | E4: TRUE
A5: AKF | B5: EO5W30 | C5: Engine Oil 5W-30 | D5: LUBRICANT | E5: TRUE
A6: AKF | B6: OILFIL | C6: Oil Filter | D6: OTHER | E6: TRUE
A7: AKF | B7: BRKPAD | C7: Brake Pads | D7: OTHER | E7: TRUE
A8: NBF | B8: S95 | C8: Super 95 | D8: FUEL | E8: TRUE
A9: NBF | B9: S91 | C9: Super 91 | D9: FUEL | E9: TRUE
A10: NBF | B10: AGO | C10: Diesel | D10: FUEL | E10: TRUE
A11: NBF | B11: EO15W40 | C11: Engine Oil 15W-40 | D11: LUBRICANT | E11: TRUE
A12: NBF | B12: AIRFIL | C12: Air Filter | D12: OTHER | E12: TRUE

Sheet Product Prices
A1: companyCode | B1: stationCode | C1: productCode | D1: effectiveFrom | E1: price | F1: unit
A2: AKF | B2: AKF-AC | C2: S95 | D2: 19-Jun-2026 | E2: 15.31 | F2: Litre
A3: AKF | B3: AKF-AC | C3: S91 | D3: 19-Jun-2026 | E3: 14.85 | F3: Litre
A4: AKF | B4: AKF-AC | C4: AGO | D4: 19-Jun-2026 | E4: 15.95 | F4: Litre
A5: AKF | B5: AKF-AC | C5: EO5W30 | D5: 19-Jun-2026 | E5: 95 | F5: Each
A6: AKF | B6: AKF-AC | C6: OILFIL | D6: 19-Jun-2026 | E6: 80 | F6: Each
A7: AKF | B7: AKF-AC | C7: BRKPAD | D7: 19-Jun-2026 | E7: 220 | F7: Each
A8: AKF | B8: AKF-KU | C8: S95 | D8: 19-Jun-2026 | E8: 15.29 | F8: Litre
A9: AKF | B9: AKF-KU | C9: S91 | D9: 19-Jun-2026 | E9: 14.82 | F9: Litre
A10: AKF | B10: AKF-KU | C10: AGO | D10: 19-Jun-2026 | E10: 15.9 | F10: Litre
A11: AKF | B11: AKF-KU | C11: EO5W30 | D11: 19-Jun-2026 | E11: 95 | F11: Each
A12: AKF | B12: AKF-KU | C12: OILFIL | D12: 19-Jun-2026 | E12: 80 | F12: Each
A13: NBF | B13: NBF-TA | C13: S95 | D13: 19-Jun-2026 | E13: 15.35 | F13: Litre
... A17: NBF | B17: NBF-TA | C17: AIRFIL | D17: 19-Jun-2026 | E17: 65 | F17: Each

Sheet Tanks
A1: companyCode | B1: stationCode | C1: tankCode | D1: tankName | E1: productCode | F1: capacityLitres | G1: status
A2: AKF | B2: AKF-AC | C2: AC-T95 | D2: Tank 1 - Super 95 | E2: S95 | F2: 30000 | G2: ACTIVE
A3: AKF | B3: AKF-AC | C3: AC-T91 | D3: Tank 2 - Super 91 | E3: S91 | F3: 25000 | G3: ACTIVE
A4: AKF | B4: AKF-AC | C4: AC-TD1 | D4: Tank 3 - Diesel | E4: AGO | F4: 35000 | G4: ACTIVE
A5: AKF | B5: AKF-KU | C5: KU-T95 | D5: Tank 1 - Super 95 | E5: S95 | F5: 25000 | G5: ACTIVE
A6: AKF | B6: AKF-KU | C6: KU-TD1 | D6: Tank 2 - Diesel | E6: AGO | F6: 30000 | G6: ACTIVE
A7: NBF | B7: NBF-TA | C7: TA-T91 | D7: Tank 1 - Super 91 | E7: S91 | F7: 22000 | G7: ACTIVE
A8: NBF | B8: NBF-TA | C8: TA-TD1 | D8: Tank 2 - Diesel | E8: AGO | F8: 30000 | G8: ACTIVE

Sheet Pumps
A1: companyCode | B1: stationCode | C1: pumpCode | D1: pumpName | E1: status
A2: AKF | B2: AKF-AC | C2: AC-P1 | D2: Pump 1 | E2: ACTIVE
A3: AKF | B3: AKF-AC | C3: AC-P2 | D3: Pump 2 | E3: ACTIVE
A4: AKF | B4: AKF-KU | C4: KU-P1 | D4: Pump 1 | E4: ACTIVE
A5: AKF | B5: AKF-KU | C5: KU-P2 | D5: Pump 2 | E5: ACTIVE
A6: NBF | B6: NBF-TA | C6: TA-P1 | D6: Pump 1 | E6: ACTIVE

Sheet Nozzles
A1: companyCode | B1: stationCode | C1: pumpCode | D1: nozzleCode | E1: nozzleName | F1: productCode | G1: meterCode | H1: status
A2: AKF | B2: AKF-AC | C2: AC-P1 | D2: AC-P1-A | E2: Pump 1 - Nozzle A | F2: S95 | G2: M-AC-95-A | H2: ACTIVE
A3: AKF | B3: AKF-AC | C3: AC-P1 | D3: AC-P1-B | E3: Pump 1 - Nozzle B | F3: AGO | G3: M-AC-D-B | H3: ACTIVE
A4: AKF | B4: AKF-AC | C4: AC-P2 | D4: AC-P2-A | E4: Pump 2 - Nozzle A | F4: S91 | G4: M-AC-91-A | H4: ACTIVE
A5: AKF | B5: AKF-AC | C5: AC-P2 | D5: AC-P2-B | E5: Pump 2 - Nozzle B | F5: AGO | G5: M-AC-D-C | H5: ACTIVE
A6: AKF | B6: AKF-KU | C6: KU-P1 | D6: KU-P1-A | E6: Pump 1 - Nozzle A | F6: S95 | G6: M-KU-95-A | H6: ACTIVE
A7: AKF | B7: AKF-KU | C7: KU-P1 | D7: KU-P1-B | E7: Pump 1 - Nozzle B | F7: AGO | G7: M-KU-D-B | H7: ACTIVE
A8: AKF | B8: AKF-KU | C8: KU-P2 | D8: KU-P2-A | E8: Pump 2 - Nozzle A | F8: AGO | G8: M-KU-D-C | H8: ACTIVE
A9: NBF | B9: NBF-TA | C9: TA-P1 | D9: TA-P1-A | E9: Pump 1 - Nozzle A | F9: S91 | G9: M-TA-91-A | H9: ACTIVE
A10: NBF | B10: NBF-TA | C10: TA-P1 | D10: TA-P1-B | E10: Pump 1 - Nozzle B | F10: AGO | G10: M-TA-D-B | H10: ACTIVE

Sheet Debtors
A1: companyCode | B1: stationCode | C1: debtorCode | D1: debtorName | E1: phone | F1: email | G1: creditLimit | H1: openingBalance | I1: status
A2: AKF | B2: AKF-AC | C2: AC-DBT-01 | D2: Mensah Logistics | E2: 244001100 | F2: accounts@mensahlogistics.com | G2: 10000 | H2: 1250 | I2: ACTIVE
A3: AKF | B3: AKF-KU | C3: KU-DBT-01 | D3: Ridge Construction | E3: 205002200 | F3: payables@ridgeconstruction.com | G3: 15000 | H3: 0 | I3: ACTIVE
A4: NBF | B4: NBF-TA | C4: TA-DBT-01 | D4: Savannah Haulage | E4: 0277003300 | F4: finance@savannahhaulage.com | G4: 8000 | H4: 780 | I4: ACTIVE

Sheet Daily Sessions
A1: companyCode | B1: stationCode | C1: businessDate | D1: shift | E1: openedByEmail | F1: status
A2: AKF | B2: AKF-AC | C2: 19-Jun-2026 | D2: DAY | E2: kojo.armah@akwaabaenergy.com | F2: OPEN
A3: AKF | B3: AKF-KU | C3: 19-Jun-2026 | D3: DAY | E3: esi.arthur@akwaabaenergy.com | F3: OPEN
A4: NBF | B4: NBF-TA | C4: 19-Jun-2026 | D4: DAY | E4: issah.mohammed@northbridgefuels.com | F4: OPEN

Sheet Pump Sales
A1: companyCode | B1: stationCode | C1: businessDate | D1: shift | E1: nozzleCode | F1: productCode | G1: openingMeter | H1: closingMeter | I1: litresSoldFormula | J1: unitPrice | K1: expectedAmountFormula | L1: cashReceived | M1: goCardVisa | N1: coupon | O1: ghqrMomo | P1: creditSales | Q1: varianceFormula | R1: attendantEmail | S1: remarks
A2: AKF | B2: AKF-AC | C2: 19-Jun-2026 | D2: DAY | E2: AC-P1-A | F2: S95 | G2: 49784.99 | H2: 50084.99 | I2: =H2-G2 -> 300 | J2: 15.31 | K2: =I2*J2 -> 4593 | L2: 3000 | M2: 500 | N2: 300 | O2: 793 | P2: 0 | Q2: =SUM(L2:P2)-K2 -> 0 | R2: adwoa.serwaa@akwaabaenergy.com | S2: Balanced
A3: AKF | B3: AKF-AC | C3: 19-Jun-2026 | D3: DAY | E3: AC-P1-B | F3: AGO | G3: 22980.8 | H3: 23230.8 | I3: =H3-G3 -> 250 | J3: 15.95 | K3: =I3*J3 -> 3987.5 | L3: 2500 | M3: 600 | N3: 0 | O3: 887.5 | P3: 0 | Q3: =SUM(L3:P3)-K3 -> 0 | R3: adwoa.serwaa@akwaabaenergy.com | S3: Balanced
A4: AKF | B4: AKF-AC | C4: 19-Jun-2026 | D4: DAY | E4: AC-P2-A | F4: S91 | G4: 18840 | H4: 19020 | I4: =H4-G4 -> 180 | J4: 14.85 | K4: =I4*J4 -> 2673 | L4: 1800 | M4: 0 | N4: 200 | O4: 300 | P4: 373 | Q4: =SUM(L4:P4)-K4 -> 0 | R4: adwoa.serwaa@akwaabaenergy.com | S4: Credit sale to Mensah Logistics
A5: AKF | B5: AKF-AC | C5: 19-Jun-2026 | D5: DAY | E5: AC-P2-B | F5: AGO | G5: 44120 | H5: 44340 | I5: =H5-G5 -> 220 | J5: 15.95 | K5: =I5*J5 -> 3509 | L5: 2400 | M5: 500 | N5: 0 | O5: 609 | P5: 0 | Q5: =SUM(L5:P5)-K5 -> 0 | R5: adwoa.serwaa@akwaabaenergy.com | S5: Balanced
A6: AKF | B6: AKF-KU | C6: 19-Jun-2026 | D6: DAY | E6: KU-P1-A | F6: S95 | G6: 10200 | H6: 10410 | I6: =H6-G6 -> 210 | J6: 15.29 | K6: =I6*J6 -> 3210.9 | L6: 2200 | M6: 500 | N6: 0 | O6: 510.9 | P6: 0 | Q6: =SUM(L6:P6)-K6 -> 0 | R6: esi.arthur@akwaabaenergy.com | S6: Balanced
A7: AKF | B7: AKF-KU | C7: 19-Jun-2026 | D7: DAY | E7: KU-P1-B | F7: AGO | G7: 7850 | H7: 8050 | I7: =H7-G7 -> 200 | J7: 15.9 | K7: =I7*J7 -> 3180 | L7: 2400 | M7: 0 | N7: 250 | O7: 530 | P7: 0 | Q7: =SUM(L7:P7)-K7 -> 0 | R7: esi.arthur@akwaabaenergy.com | S7: Balanced
A8: AKF | B8: AKF-KU | C8: 19-Jun-2026 | D8: DAY | E8: KU-P2-A | F8: AGO | G8: 6400 | H8: 6550 | I8: =H8-G8 -> 150 | J8: 15.9 | K8: =I8*J8 -> 2385 | L8: 1800 | M8: 0 | N8: 0 | O8: 585 | P8: 0 | Q8: =SUM(L8:P8)-K8 -> 0 | R8: esi.arthur@akwaabaenergy.com | S8: Balanced
A9: NBF | B9: NBF-TA | C9: 19-Jun-2026 | D9: DAY | E9: TA-P1-A | F9: S91 | G9: 33010 | H9: 33160 | I9: =H9-G9 -> 150 | J9: 14.9 | K9: =I9*J9 -> 2235 | L9: 1600 | M9: 300 | N9: 0 | O9: 335 | P9: 0 | Q9: =SUM(L9:P9)-K9 -> 0 | R9: issah.mohammed@northbridgefuels.com | S9: Balanced
A10: NBF | B10: NBF-TA | C10: 19-Jun-2026 | D10: DAY | E10: TA-P1-B | F10: AGO | G10: 21000 | H10: 21210 | I10: =H10-G10 -> 210 | J10: 16 | K10: =I10*J10 -> 3360 | L10: 2500 | M10: 0 | N10: 300 | O10: 560 | P10: 0 | Q10: =SUM(L10:P10)-K10 -> 0 | R10: issah.mohammed@northbridgefuels.com | S10: Balanced

Sheet Payment Details
A1: companyCode | B1: stationCode | C1: businessDate | D1: shift | E1: channel | F1: amount | G1: customerName | H1: attendantName | I1: referenceNumber | J1: serialNumber | K1: status | L1: remarks
A2: AKF | B2: AKF-AC | C2: 19-Jun-2026 | D2: DAY | E2: GO_CARD | F2: 1600 | G2: Walk-in customers | H2: Adwoa Serwaa | I2: GC-AC-001 | K2: SUBMITTED_TO_HQ | L2: Aggregated GO Card/Visa from pump sales
A3: AKF | B3: AKF-AC | C3: 19-Jun-2026 | D3: DAY | E3: GOIL_COUPON | F3: 500 | G3: Corporate coupons | H3: Adwoa Serwaa | I3: CP-AC-001 | J3: CPS-001-005 | K3: SUBMITTED_TO_HQ | L3: Aggregated coupons
A4: AKF | B4: AKF-AC | C4: 19-Jun-2026 | D4: DAY | E4: GHQR | F4: 2589.5 | G4: Mobile payments | H4: Adwoa Serwaa | I4: GHQR-AC-001 | K4: SUBMITTED_TO_HQ | L4: Aggregated GHQR/MoMo
A5: AKF | B5: AKF-KU | C5: 19-Jun-2026 | D5: DAY | E5: GO_CARD | F5: 500 | G5: Walk-in customers | H5: Esi Arthur | I5: GC-KU-001 | K5: SUBMITTED_TO_HQ
A6: AKF | B6: AKF-KU | C6: 19-Jun-2026 | D6: DAY | E6: GOIL_COUPON | F6: 250 | G6: Corporate coupons | H6: Esi Arthur | I6: CP-KU-001 | J6: KUC-01 | K6: SUBMITTED_TO_HQ
A7: AKF | B7: AKF-KU | C7: 19-Jun-2026 | D7: DAY | E7: GHQR | F7: 1625.9 | G7: Mobile payments | H7: Esi Arthur | I7: GHQR-KU-001 | K7: SUBMITTED_TO_HQ
A8: NBF | B8: NBF-TA | C8: 19-Jun-2026 | D8: DAY | E8: GO_CARD | F8: 300 | G8: Walk-in customers | H8: Issah Mohammed | I8: GC-TA-001 | K8: SUBMITTED_TO_HQ
A9: NBF | B9: NBF-TA | C9: 19-Jun-2026 | D9: DAY | E9: GOIL_COUPON | F9: 300 | G9: Corporate coupons | H9: Issah Mohammed | I9: CP-TA-001 | J9: TAC-01 | K9: SUBMITTED_TO_HQ
A10: NBF | B10: NBF-TA | C10: 19-Jun-2026 | D10: DAY | E10: GHQR | F10: 560 | G10: Mobile payments | H10: Issah Mohammed | I10: GHQR-TA-001 | K10: SUBMITTED_TO_HQ

Sheet Debtor Ledger
A1: companyCode | B1: stationCode | C1: businessDate | D1: shift | E1: debtorCode | F1: type | G1: amount | H1: paymentMethod | I1: reference | J1: cashReceivedDate | K1: remarks
A2: AKF | B2: AKF-AC | C2: 19-Jun-2026 | D2: DAY | E2: AC-DBT-01 | F2: SALE | G2: 373 | I2: CR-AC-001 | K2: Fuel credit sale from Pump 2 Nozzle A
A3: AKF | B3: AKF-AC | C3: 19-Jun-2026 | D3: DAY | E3: AC-DBT-01 | F3: PAYMENT | G3: 500 | H3: CASH | I3: PAY-AC-001 | J3: 19-Jun-2026 | K3: Part payment received at station
A4: NBF | B4: NBF-TA | C4: 19-Jun-2026 | D4: DAY | E4: TA-DBT-01 | F4: PAYMENT | G4: 300 | H4: MOMO | I4: PAY-TA-001 | J4: 19-Jun-2026 | K4: MoMo payment received

Sheet Product Discharge
A1: companyCode | B1: stationCode | C1: businessDate | D1: shift | E1: tankCode | F1: productCode | G1: supplierName | H1: invoiceNumber | I1: vehicleReg | J1: driverName | K1: beforeTankLitres | L1: invoiceMeasurement | M1: productDischargedLitres | N1: adjustmentTopUpLitres | O1: expectedTankAfterDischargeFormula | P1: afterTankLitres | Q1: dischargeVarianceFormula | R1: supervisorName | S1: couplingHeightCm | T1: calibrationCertificate | U1: tbar
A2: AKF | B2: AKF-AC | C2: 19-Jun-2026 | D2: DAY | E2: AC-T95 | F2: S95 | G2: GOIL Depot Tema | H2: INV-AC-9501 | I2: GT 2245-23 | J2: Yaw Frimpong | K2: 18200 | L2: 5000 | M2: 5000 | N2: 0 | O2: =K2+M2+N2 -> 23200 | P2: 23200 | Q2: =P2-O2 -> 0 | R2: Kojo Armah | S2: 12.5 | T2: CAL-2026-AC-01 | U2: 4.2
A3: NBF | B3: NBF-TA | C3: 19-Jun-2026 | D3: DAY | E3: TA-TD1 | F3: AGO | G3: GOIL Depot Tamale | H3: INV-TA-D001 | I3: NR 8890-22 | J3: Ibrahim Fuseini | K3: 14500 | L3: 8000 | M3: 7900 | N3: 100 | O3: =K3+M3+N3 -> 22500 | P3: 22500 | Q3: =P3-O3 -> 0 | R3: Issah Mohammed | S3: 11.8 | T3: CAL-2026-TA-03 | U3: 4

Sheet Tank Dipping
A1: companyCode | B1: stationCode | C1: businessDate | D1: shift | E1: tankCode | F1: productCode | G1: openingStockLitres | H1: receiptsLitres | I1: closingDipCm | J1: closingStockLitres | K1: meterSoldLitres | L1: expectedClosingFormula | M1: varianceLitresFormula | N1: waterTestStatus | O1: supervisorEmail
A2: AKF | B2: AKF-AC | C2: 19-Jun-2026 | D2: DAY | E2: AC-T95 | F2: S95 | G2: 18200 | H2: 5000 | I2: 286.3 | J2: 22900 | K2: 300 | L2: =G2+H2-K2 -> 22900 | M2: =J2-L2 -> 0 | N2: CLEAR | O2: kojo.armah@akwaabaenergy.com
A3: AKF | B3: AKF-AC | C3: 19-Jun-2026 | D3: DAY | E3: AC-T91 | F3: S91 | G3: 14800 | H3: 0 | I3: 180.5 | J3: 14620 | K3: 180 | L3: =G3+H3-K3 -> 14620 | M3: =J3-L3 -> 0 | N3: CLEAR | O3: kojo.armah@akwaabaenergy.com
A4: AKF | B4: AKF-AC | C4: 19-Jun-2026 | D4: DAY | E4: AC-TD1 | F4: AGO | G4: 20100 | H4: 0 | I4: 246.2 | J4: 19630 | K4: 470 | L4: =G4+H4-K4 -> 19630 | M4: =J4-L4 -> 0 | N4: CLEAR | O4: kojo.armah@akwaabaenergy.com
A5: AKF | B5: AKF-KU | C5: 19-Jun-2026 | D5: DAY | E5: KU-T95 | F5: S95 | G5: 12950 | H5: 0 | I5: 164.1 | J5: 12740 | K5: 210 | L5: =G5+H5-K5 -> 12740 | M5: =J5-L5 -> 0 | N5: CLEAR | O5: esi.arthur@akwaabaenergy.com
A6: AKF | B6: AKF-KU | C6: 19-Jun-2026 | D6: DAY | E6: KU-TD1 | F6: AGO | G6: 17600 | H6: 0 | I6: 220.9 | J6: 17250 | K6: 350 | L6: =G6+H6-K6 -> 17250 | M6: =J6-L6 -> 0 | N6: CLEAR | O6: esi.arthur@akwaabaenergy.com
A7: NBF | B7: NBF-TA | C7: 19-Jun-2026 | D7: DAY | E7: TA-T91 | F7: S91 | G7: 11900 | H7: 0 | I7: 154.2 | J7: 11750 | K7: 150 | L7: =G7+H7-K7 -> 11750 | M7: =J7-L7 -> 0 | N7: CLEAR | O7: issah.mohammed@northbridgefuels.com
A8: NBF | B8: NBF-TA | C8: 19-Jun-2026 | D8: DAY | E8: TA-TD1 | F8: AGO | G8: 14500 | H8: 8000 | I8: 290.4 | J8: 22290 | K8: 210 | L8: =G8+H8-K8 -> 22290 | M8: =J8-L8 -> 0 | N8: CLEAR | O8: issah.mohammed@northbridgefuels.com

Sheet Expenditure
A1: companyCode | B1: stationCode | C1: businessDate | D1: shift | E1: category | F1: amount | G1: paidBy | H1: voucherReference | I1: receiptAttached | J1: description
A2: AKF | B2: AKF-AC | C2: 19-Jun-2026 | D2: DAY | E2: Generator Fuel | F2: 350 | G2: Kojo Armah | H2: EXP-AC-001 | I2: TRUE | J2: Generator support fuel
A3: AKF | B3: AKF-AC | C3: 19-Jun-2026 | D3: DAY | E3: Cleaning | F3: 120 | G3: Kojo Armah | H3: EXP-AC-002 | I3: FALSE | J3: Cleaning supplies
A4: AKF | B4: AKF-KU | C4: 19-Jun-2026 | D4: DAY | E4: Transport | F4: 180 | G4: Esi Arthur | H4: EXP-KU-001 | I4: TRUE | J4: Station errands
A5: NBF | B5: NBF-TA | C5: 19-Jun-2026 | D5: DAY | E5: Security | F5: 200 | G5: Issah Mohammed | H5: EXP-TA-001 | I5: TRUE | J5: Night security payment

Sheet Sheet1

Sheet Mart Sales
A1: companyCode | B1: stationCode | C1: businessDate | D1: shift | E1: openingCash | F1: cardSales | G1: cashSales | H1: mobileMoney | I1: returns | J1: netMartSalesFormula | K1: physicalCashCount | L1: cashVarianceFormula | M1: remarks
A2: AKF | B2: AKF-AC | C2: 19-Jun-2026 | D2: DAY | E2: 100 | F2: 800 | G2: 500 | H2: 250 | I2: 40 | J2: =F2+G2+H2-I2 -> 1510 | K2: 600 | L2: =K2-(E2+G2) -> 0 | M2: Balanced
A3: AKF | B3: AKF-KU | C3: 19-Jun-2026 | D3: DAY | E3: 100 | F3: 450 | G3: 360 | H3: 140 | I3: 0 | J3: =F3+G3+H3-I3 -> 950 | K3: 460 | L3: =K3-(E3+G3) -> 0 | M3: Balanced
A4: NBF | B4: NBF-TA | C4: 19-Jun-2026 | D4: DAY | E4: 80 | F4: 280 | G4: 320 | H4: 100 | I4: 20 | J4: =F4+G4+H4-I4 -> 680 | K4: 400 | L4: =K4-(E4+G4) -> 0 | M4: Balanced

Sheet Lube Bay Setup
A1: companyCode | B1: stationCode | C1: serviceType | D1: vehicleCategory | E1: defaultLabourCharge | F1: isActive
A2: AKF | B2: AKF-AC | C2: Oil Change | D2: Salon and Sedans | E2: 60 | F2: TRUE
A3: AKF | B3: AKF-AC | C3: Wheel Rotation | D3: SUV and Crossovers | E3: 80 | F3: TRUE
A4: AKF | B4: AKF-KU | C4: Oil Change | D4: Light Commercial Vehicles | E4: 75 | F4: TRUE
A5: NBF | B5: NBF-TA | C5: Oil Change | D5: Heavy Duty & Commercial Trucks | E5: 120 | F5: TRUE

Sheet Lube Bay Sales
A1: companyCode | B1: stationCode | C1: businessDate | D1: shift | E1: vehicleReg | F1: customerName | G1: serviceType | H1: vehicleCategory | I1: productCode | J1: quantity | K1: unitPrice | L1: productAmountFormula | M1: labourCharge | N1: discount | O1: totalExpectedFormula | P1: paymentMode | Q1: cashAmount | R1: cardAmount | S1: momoAmount | T1: creditAmount | U1: varianceFormula | V1: technicianName | W1: supervisorName
A2: AKF | B2: AKF-AC | C2: 19-Jun-2026 | D2: DAY | E2: GR 4412-22 | F2: Yaw Appiah | G2: Oil Change | H2: Salon and Sedans | I2: EO5W30 | J2: 4 | K2: 95 | L2: =J2*K2 -> 380 | M2: 60 | N2: 20 | O2: =L2+M2-N2 -> 420 | P2: CASH | Q2: 420 | R2: 0 | S2: 0 | T2: 0 | U2: =SUM(Q2:T2)-O2 -> 0 | V2: Michael Tetteh | W2: Kojo Armah
A3: AKF | B3: AKF-AC | C3: 19-Jun-2026 | D3: DAY | E3: GW 9090-20 | F3: Akosua Manu | G3: Wheel Rotation | H3: SUV and Crossovers | J3: 0 | K3: 0 | L3: =J3*K3 -> 0 | M3: 80 | N3: 0 | O3: =L3+M3-N3 -> 80 | P3: MOMO | Q3: 0 | R3: 0 | S3: 80 | T3: 0 | U3: =SUM(Q3:T3)-O3 -> 0 | V3: Michael Tetteh | W3: Kojo Armah
A4: NBF | B4: NBF-TA | C4: 19-Jun-2026 | D4: DAY | E4: NR 7788-21 | F4: Hassan Iddrisu | G4: Oil Change | H4: Heavy Duty & Commercial Trucks | I4: EO15W40 | J4: 6 | K4: 105 | L4: =J4*K4 -> 630 | M4: 120 | N4: 0 | O4: =L4+M4-N4 -> 750 | P4: CARD | Q4: 0 | R4: 750 | S4: 0 | T4: 0 | U4: =SUM(Q4:T4)-O4 -> 0 | V4: Mubarak Adams | W4: Issah Mohammed

Sheet Cash Collection
A1: companyCode | B1: stationCode | C1: businessDate | D1: shift | E1: pumpCash | F1: debtorCashPayments | G1: actualExpenditure | H1: expectedCashToBankFormula | I1: alreadyBankedBeforeThisEntry | J1: amountToBank | K1: varianceFormula | L1: bankCollectionDate | M1: collectionReference | N1: bankSignatureName | O1: supervisorSignatureName
A2: AKF | B2: AKF-AC | C2: 19-Jun-2026 | D2: DAY | E2: 9700 | F2: 500 | G2: 470 | H2: =E2+F2-G2 -> 9730 | I2: 0 | J2: 9730 | K2: =J2-H2+I2 -> 0 | L2: 19-Jun-2026 | M2: BANK-AC-001 | N2: Abena Banku | O2: Kojo Armah
A3: AKF | B3: AKF-KU | C3: 19-Jun-2026 | D3: DAY | E3: 6400 | F3: 0 | G3: 180 | H3: =E3+F3-G3 -> 6220 | I3: 0 | J3: 6220 | K3: =J3-H3+I3 -> 0 | L3: 19-Jun-2026 | M3: BANK-KU-001 | N3: Kwame Adu | O3: Esi Arthur
A4: NBF | B4: NBF-TA | C4: 19-Jun-2026 | D4: DAY | E4: 4100 | F4: 0 | G4: 200 | H4: =E4+F4-G4 -> 3900 | I4: 0 | J4: 3900 | K4: =J4-H4+I4 -> 0 | L4: 19-Jun-2026 | M4: BANK-TA-001 | N4: Mariam Adam | O4: Issah Mohammed

Sheet Expected Reconciliation
A1: companyCode | B1: stationCode | C1: businessDate | D1: pumpExpected | E1: pumpCash | F1: hqDirect | G1: creditSales | H1: debtorCashPayments | I1: actualExpenditure | J1: expectedCashToBank | K1: cashBanked | L1: bankingVariance | M1: martNetSales | N1: martCashVariance | O1: tankVarianceLitres | P1: dischargeVarianceLitres
A2: AKF | B2: AKF-AC | C2: 19-Jun-2026 | D2: =SUMIFS('Pump Sales'!K:K,'Pump Sales'!A:A,A2,'Pump Sales'!B:B,B2) -> 14762.5 | E2: =SUMIFS('Pump Sales'!L:L,'Pump Sales'!A:A,A2,'Pump Sales'!B:B,B2) -> 9700 | F2: =SUMIFS('Pump Sales'!M:M,'Pump Sales'!A:A,A2,'Pump Sales'!B:B,B2)+SUMIFS('Pump Sales'!N:N,'Pump Sales'!A:A,A2,'Pump Sales'!B:B,B2)+SUMIFS('Pump Sales'!O:O,'Pump Sales'!A:A,A2,'Pump Sales'!B:B,B2) -> 4689.5 | G2: =SUMIFS('Pump Sales'!P:P,'Pump Sales'!A:A,A2,'Pump Sales'!B:B,B2) -> 373 | H2: =SUMIFS('Debtor Ledger'!G:G,'Debtor Ledger'!A:A,A2,'Debtor Ledger'!B:B,B2,'Debtor Ledger'!F:F,"PAYMENT",'Debtor Ledger'!H:H,"CASH") -> 500 | I2: =SUMIFS(Expenditure!F:F,Expenditure!A:A,A2,Expenditure!B:B,B2) -> 470 | J2: =E2+H2-I2 -> 9730 | K2: =SUMIFS('Cash Collection'!J:J,'Cash Collection'!A:A,A2,'Cash Collection'!B:B,B2) -> 9730 | L2: =K2-J2 -> 0 | M2: =SUMIFS('Mart Sales'!J:J,'Mart Sales'!A:A,A2,'Mart Sales'!B:B,B2) -> 1510 | N2: =SUMIFS('Mart Sales'!L:L,'Mart Sales'!A:A,A2,'Mart Sales'!B:B,B2) -> 0 | O2: =SUMIFS('Tank Dipping'!M:M,'Tank Dipping'!A:A,A2,'Tank Dipping'!B:B,B2) -> 0 | P2: =SUMIFS('Product Discharge'!Q:Q,'Product Discharge'!A:A,A2,'Product Discharge'!B:B,B2) -> 0
A3: AKF | B3: AKF-KU | C3: 19-Jun-2026 | D3: =SUMIFS('Pump Sales'!K:K,'Pump Sales'!A:A,A3,'Pump Sales'!B:B,B3) -> 8775.9 | E3: =SUMIFS('Pump Sales'!L:L,'Pump Sales'!A:A,A3,'Pump Sales'!B:B,B3) -> 6400 | F3: =SUMIFS('Pump Sales'!M:M,'Pump Sales'!A:A,A3,'Pump Sales'!B:B,B3)+SUMIFS('Pump Sales'!N:N,'Pump Sales'!A:A,A3,'Pump Sales'!B:B,B3)+SUMIFS('Pump Sales'!O:O,'Pump Sales'!A:A,A3,'Pump Sales'!B:B,B3) -> 2375.9 | G3: =SUMIFS('Pump Sales'!P:P,'Pump Sales'!A:A,A3,'Pump Sales'!B:B,B3) -> 0 | H3: =SUMIFS('Debtor Ledger'!G:G,'Debtor Ledger'!A:A,A3,'Debtor Ledger'!B:B,B3,'Debtor Ledger'!F:F,"PAYMENT",'Debtor Ledger'!H:H,"CASH") -> 0 | I3: =SUMIFS(Expenditure!F:F,Expenditure!A:A,A3,Expenditure!B:B,B3) -> 180 | J3: =E3+H3-I3 -> 6220 | K3: =SUMIFS('Cash Collection'!J:J,'Cash Collection'!A:A,A3,'Cash Collection'!B:B,B3) -> 6220 | L3: =K3-J3 -> 0 | M3: =SUMIFS('Mart Sales'!J:J,'Mart Sales'!A:A,A3,'Mart Sales'!B:B,B3) -> 950 | N3: =SUMIFS('Mart Sales'!L:L,'Mart Sales'!A:A,A3,'Mart Sales'!B:B,B3) -> 0 | O3: =SUMIFS('Tank Dipping'!M:M,'Tank Dipping'!A:A,A3,'Tank Dipping'!B:B,B3) -> 0 | P3: =SUMIFS('Product Discharge'!Q:Q,'Product Discharge'!A:A,A3,'Product Discharge'!B:B,B3) -> 0
A4: NBF | B4: NBF-TA | C4: 19-Jun-2026 | D4: =SUMIFS('Pump Sales'!K:K,'Pump Sales'!A:A,A4,'Pump Sales'!B:B,B4) -> 5595 | E4: =SUMIFS('Pump Sales'!L:L,'Pump Sales'!A:A,A4,'Pump Sales'!B:B,B4) -> 4100 | F4: =SUMIFS('Pump Sales'!M:M,'Pump Sales'!A:A,A4,'Pump Sales'!B:B,B4)+SUMIFS('Pump Sales'!N:N,'Pump Sales'!A:A,A4,'Pump Sales'!B:B,B4)+SUMIFS('Pump Sales'!O:O,'Pump Sales'!A:A,A4,'Pump Sales'!B:B,B4) -> 1495 | G4: =SUMIFS('Pump Sales'!P:P,'Pump Sales'!A:A,A4,'Pump Sales'!B:B,B4) -> 0 | H4: =SUMIFS('Debtor Ledger'!G:G,'Debtor Ledger'!A:A,A4,'Debtor Ledger'!B:B,B4,'Debtor Ledger'!F:F,"PAYMENT",'Debtor Ledger'!H:H,"CASH") -> 0 | I4: =SUMIFS(Expenditure!F:F,Expenditure!A:A,A4,Expenditure!B:B,B4) -> 200 | J4: =E4+H4-I4 -> 3900 | K4: =SUMIFS('Cash Collection'!J:J,'Cash Collection'!A:A,A4,'Cash Collection'!B:B,B4) -> 3900 | L4: =K4-J4 -> 0 | M4: =SUMIFS('Mart Sales'!J:J,'Mart Sales'!A:A,A4,'Mart Sales'!B:B,B4) -> 680 | N4: =SUMIFS('Mart Sales'!L:L,'Mart Sales'!A:A,A4,'Mart Sales'!B:B,B4) -> 0 | O4: =SUMIFS('Tank Dipping'!M:M,'Tank Dipping'!A:A,A4,'Tank Dipping'!B:B,B4) -> 0 | P4: =SUMIFS('Product Discharge'!Q:Q,'Product Discharge'!A:A,A4,'Product Discharge'!B:B,B4) -> 0

Sheet Import Validation Rules
A1: Area | B1: Rule
A2: Tenant isolation | B2: Every row must include companyCode, and station-scoped rows must include stationCode.
A3: Business codes | B3: Import should resolve companyCode, stationCode, productCode, tankCode, pumpCode, nozzleCode, debtorCode, and user email to database IDs.
A4: Users | B4: Do not import real passwords. Generate temporary passwords and force reset on first login.
A5: Cash collection | B5: Reject new amountToBank when remaining expected cash is zero/negative or the amount exceeds remaining expected cash.
A6: Expenditure | B6: Amount is actual expenditure only. Do not use paymentToBank for returned imprest.
A7: Product discharge | B7: expectedTankAfterDischarge = beforeTankLitres + productDischargedLitres + adjustmentTopUpLitres.
A8: Tank dipping | B8: varianceLitres = closingStockLitres - (openingStockLitres + receiptsLitres - meterSoldLitres).
A9: Pump sales | B9: Expected amount = litres sold * station product price. Total collection channels should equal expected amount unless a variance is intentional.
A10: Backup restore | B10: Restore to existing tenant must be validate-first and require explicit confirmation before data replacement.

Sheet Control Summary
A1: FuelStation OS E2E Summary
A3: Metric | B3: Akwaaba Accra | C3: Akwaaba Kumasi | D3: Northbridge Tamale | F3: Expected Outcome | G3: Owner Review | H3: Notes
A4: Banking Variance | B4: 0 | C4: 0 | D4: 0 | F4: All zero | G4: Pass when all zero | H4: Calculated in Expected Reconciliation
A5: Tank Variance (L) | B5: 0 | C5: 0 | D5: 0 | F5: All zero | G5: Pass when all zero | H5: Tank Dipping should reconcile to meter sold
A6: Discharge Variance (L) | B6: 0 | D6: 0 | F6: Zero where discharge exists | G6: Pass when zero | H6: Top-up is included for Northbridge
A8: Manual Test Flow | B8: Page | C8: Expected result
A9: 1 | B9: Super Admin / Platform | C9: Create tenants AKF and NBF or validate importer creates them.
A10: 2 | B10: Setup | C10: Create stations, products, prices, tanks, pumps, nozzles, debtors, users.
A11: 3 | B11: Command Center | C11: Open a daily session for each station.
A12: 4 | B12: Forecourt/Cash/Mart/Lube | C12: Enter the day using operational tabs.
A13: 5 | B13: Daily Close | C13: All required workflows complete; variances align with Expected Reconciliation.
A14: 6 | B14: Reports/Admin | C14: Confirm audit trail and tenant isolation.
